taxopy/__init__.py
taxopy/core.py
taxopy/exceptions.py
taxopy/utilities.py
taxopy-0.14.0.dist-info/LICENSE
taxopy-0.14.0.dist-info/WHEEL
taxopy-0.14.0.dist-info/METADATA
taxopy-0.14.0.dist-info/RECORD
