Metadata-Version: 2.1
Name: taxopy
Version: 0.14.0
Summary: A Python package for obtaining complete lineages and the lowest common ancestor (LCA) from a set of taxonomic identifiers.
Author-email: Antonio Camargo <antoniop.camargo@gmail.com>
Requires-Python: >=3.5
Classifier: Intended Audience :: Science/Research
Classifier: Natural Language :: English
Classifier: Topic :: Software Development :: Libraries
Classifier: Topic :: Scientific/Engineering :: Bio-Informatics
Classifier: License :: OSI Approved :: GNU General Public License (GPL)
Classifier: Programming Language :: Python :: 3
Requires-Dist: rapidfuzz ; extra == "fuzzy-matching"
Project-URL: Documentation, https://apcamargo.github.io/taxopy
Project-URL: Repository, https://github.com/apcamargo/taxopy
Provides-Extra: fuzzy-matching
